iplotlib/__init__.py
iplotlib/_version.py
iplotlib/core/__init__.py
iplotlib/core/axis.py
iplotlib/core/canvas.py
iplotlib/core/command.py
iplotlib/core/distance.py
iplotlib/core/drop_info.py
iplotlib/core/history_manager.py
iplotlib/core/impl_base.py
iplotlib/core/limits.py
iplotlib/core/marker.py
iplotlib/core/persistence.py
iplotlib/core/plot.py
iplotlib/core/property_manager.py
iplotlib/core/signal.py
iplotlib/core/commands/__init__.py
iplotlib/core/commands/axes_range.py
iplotlib/core/data/default_properties.json
iplotlib/core/tests/__init__.py
iplotlib/core/tests/test_01_property_manager.py
iplotlib/core/tests/test_02_signal.py
iplotlib/data_access/__init__.py
iplotlib/data_access/streamer.py
iplotlib/impl/__init__.py
iplotlib/impl/matplotlib/__init__.py
iplotlib/impl/matplotlib/dateFormatter.py
iplotlib/impl/matplotlib/iplotMultiCursor.py
iplotlib/impl/matplotlib/matplotlibCanvas.py
iplotlib/impl/matplotlib/qt/__init__.py
iplotlib/impl/matplotlib/qt/qtMatplotlibCanvas.py
iplotlib/impl/pyqtgraph/__init__.py
iplotlib/impl/vtk/__init__.py
iplotlib/impl/vtk/utils.py
iplotlib/impl/vtk/vtkCanvas.py
iplotlib/impl/vtk/qt/__init__.py
iplotlib/impl/vtk/qt/qtVTKCanvas.py
iplotlib/impl/vtk/tests/__init__.py
iplotlib/impl/vtk/tests/qVTKAppTestAdapter.py
iplotlib/impl/vtk/tests/test_01_null_refresh.py
iplotlib/impl/vtk/tests/test_02_canvas_sizing.py
iplotlib/impl/vtk/tests/test_03_row_inversion_simple.py
iplotlib/impl/vtk/tests/test_04_row_inversion_complex.py
iplotlib/impl/vtk/tests/test_05_canvas_simple.py
iplotlib/impl/vtk/tests/test_06_canvas_complex.py
iplotlib/impl/vtk/tests/test_07_signal_properties.py
iplotlib/impl/vtk/tests/test_08_datetime_tics_simple.py
iplotlib/impl/vtk/tests/test_09_datetime_tics_complex.py
iplotlib/impl/vtk/tests/test_10_crosshair_interactive.py
iplotlib/impl/vtk/tests/test_11_mouse_pan_interactive.py
iplotlib/impl/vtk/tests/test_12_mouse_zoom_interactive.py
iplotlib/impl/vtk/tests/vtk_hints.py
iplotlib/impl/vtk/tests/baseline/__init__.py
iplotlib-1.3.2.post1.dist-info/METADATA
iplotlib-1.3.2.post1.dist-info/WHEEL
iplotlib-1.3.2.post1.dist-info/entry_points.txt
iplotlib-1.3.2.post1.dist-info/top_level.txt
iplotlib-1.3.2.post1.dist-info/RECORD
