Metadata-Version: 2.4
Name: iplotlib
Version: 1.3.2.post1
Summary: ITER plotting library
Author-email: ITER Organization <jscabanilla@minsait.com>
Maintainer-email: Jhon Steeven Cabanilla Alvarado <jscabanilla@minsait.com>, Pablo Martin Villares <pmartin@minsait.com>, Mario Gomez Ballesteros <mgomezb@minsait.com>
License: MIT
Project-URL: Homepage, https://github.com/iplot-viz/iplotlib
Project-URL: Repository, https://github.com/iplot-viz/iplotlib.git
Project-URL: Issues, https://github.com/iplot-viz/iplotlib/issues
Keywords: IDS,CBS,Matplotlib,PyQtGraph,Data Visualization
Classifier: Programming Language :: Python :: 3
Classifier: License :: OSI Approved :: MIT License
Classifier: Operating System :: OS Independent
Requires-Python: >=3.9
Requires-Dist: iplotProcessing>=1.1.5
Requires-Dist: iplotDataAccess>=1.3.1
Requires-Dist: packaging>=20.0
Requires-Dist: matplotlib>=3.5.1
Requires-Dist: pandas>=1.2.0
Requires-Dist: PySide6>=6.2.3
Requires-Dist: vtk>=9.1.0
Requires-Dist: pyqtgraph>=0.13.7
Provides-Extra: test
Requires-Dist: pytest>=6.0; extra == "test"
Provides-Extra: docs
Requires-Dist: sphinx<7.0.0,>=6.0.0; extra == "docs"
Requires-Dist: sphinx-autosummary-accessors>=0.1.2; extra == "docs"
Requires-Dist: sphinx-immaterial<0.12,>=0.11.0; extra == "docs"
Requires-Dist: sphinx-click; extra == "docs"
